Mouritech_LoggingPerformance/LogPerformance.py
Mouritech_LoggingPerformance/__init__.py
Mouritech_LoggingPerformance/sample.py
Mouritech_LoggingPerformance/testPerformance.py
Mouritech_LoggingPerformance1-0.0.2.dist-info/LICENSE.txt
Mouritech_LoggingPerformance1-0.0.2.dist-info/METADATA
Mouritech_LoggingPerformance1-0.0.2.dist-info/WHEEL
Mouritech_LoggingPerformance1-0.0.2.dist-info/top_level.txt
Mouritech_LoggingPerformance1-0.0.2.dist-info/RECORD
